{
  "網路異常, 請稍後重新嘗試": "ネットワークエラー、後で再試行してください",
  "結束日期不可小於起起始日期": "終了日は開始日より小さくできません",
  "請至少選擇一個幣別!!": "少なくとも1つの通貨を選択してください!!",
  "正常": "正常",
  "停用": "無効",
  "無數據": "アカウント情報が見つかりません。再度確認してください。",
  "團隊會員": "会員情報閲覧",
  "帳號": "アカウント",
  "起始日期": "開始日",
  "結束日期": "終了日",
  "本日": "今日",
  "昨天": "昨日",
  "本週": "今週",
  "上週": "先週",
  "本月": "今月",
  "上月": "先月",
  "幣別": "通貨",
  "展開": "展開",
  "收合": "収納",
  "層級": "レベル",
  "上線帳號": "上位アカウント",
  "貨幣": "通貨",
  "團隊代理數": "チーム代理数",
  "團隊會員數": "チームメンバー数",
  "期間團隊新增下線數": "期間内のチーム新規下位数",
  "期間個人新增會員數": "期間内の個人新規会員数",
  "錢包餘額": "ウォレット残高",
  "狀態": "ステータス",
  "最後登入時間": "最終ログイン時間",
  "建立時間": "作成日時",
  "確認": "検索",
  "查看更多": "詳細を表示",
  "提醒": "システムメッセージ",
  "錯誤": "システムメッセージ",
  "完成": "システムメッセージ",
  "請輸入完整帳號": "完全なアカウントを入力してください"
}
